pyarn/__init__.py
pyarn/yarn.py
pyyarn-0.0.0.dist-info/licenses/LICENSE
pyyarn-0.0.0.dist-info/METADATA
pyyarn-0.0.0.dist-info/WHEEL
pyyarn-0.0.0.dist-info/top_level.txt
pyyarn-0.0.0.dist-info/RECORD
